{
	"code": 0,
	"data": {
		"image": {
			"url": ""
		},
		"voices": [
			{
				"icon": "https://raw.githubusercontent.com/mstogluk/dreamf9/main/png/tc-bayrak.png",
				"listen": "https://raw.githubusercontent.com/mstogluk/dreamf9/main/mp3/turkce.alev.ses.mp3",
				"name": {
					"default": "TÜRKÇE_SES_ALEV"
				},
				"desc": {},
				"download": "https://raw.githubusercontent.com/mstogluk/dreamf9/main/sesler/alev1.tar.gz",
				"md5sum": "336e0f1790dd154c9c9f2476fc45a5dc",
				"size": 3494034,
				"id": "TR"
			},
			{
				"icon": "https://raw.githubusercontent.com/mstogluk/dreamf9/main/png/tc-bayrak.png",
				"listen": "https://raw.githubusercontent.com/mstogluk/dreamf9/main/mp3/turkce.alev.ses.mp3",
				"name": {
					"default": "TÜRKÇE_ALEV_YÜKSEK_SES"
				},
				"desc": {},
				"download": "https://raw.githubusercontent.com/mstogluk/dreamf9/main/sesler/alev1.tar.gz",
				"md5sum": "336e0f1790dd154c9c9f2476fc45a5dc",
				"size": 3494034,
				"id": "TR2"
			},
			{
				"icon": "https://raw.githubusercontent.com/mstogluk/dreamf9/main/png/tc-bayrak.png",
				"listen": "https://raw.githubusercontent.com/mstogluk/dreamf9/main/mp3/turkce.alev.ses.mp3",
				"name": {
					"default": "TÜRKÇE_ALEV_MÜZİKLİ"
				},
				"desc": {},
				"download": "https://raw.githubusercontent.com/mstogluk/dreamf9/main/sesler/alevmuzik.tar.gz",
				"md5sum": "6f1753d60e482f450c5377b006e325ca",
				"size": 5905136,
				"id": "TR3"
			},
			{
				"icon": "https://raw.githubusercontent.com/mstogluk/dreamf9/main/png/pinar.png",
				"listen": "https://raw.githubusercontent.com/mstogluk/dreamf9/main/mp3/turkce.alev.ses.mp3",
				"name": {
					"default": "TÜRKÇE_PINAR"
				},
				"desc": {},
				"download": "https://raw.githubusercontent.com/mstogluk/dreamf9/main/sesler/pinar.tar.gz",
				"md5sum": "5534a25c670df90cfdc866c918ec753d",
				"size": 4787376,
				"id": "TR4"
			},

			{
				"icon": "https://raw.githubusercontent.com/mstogluk/dreamf9/main/Erik.png",
				"listen": "https://raw.githubusercontent.com/mstogluk/dreamf9/main/erikdali.mp3",
				"name": {
					"default": "Erik Dalı"
				},
				"desc": {},
				"download": "https://raw.githubusercontent.com/mstogluk/dreamf9/main/sesler/erikdali.tar.gz",
				"md5sum": "d6aad879f1e2121265f7194a15029fc1",
				"size": 7108687,
				"id": "ED"
			}
		]
	}
} 
